<?xml version="1.0" encoding="UTF-8" standalone="no"?>
<!DOCTYPE tiles-definitions PUBLIC "-//Apache Software Foundation//DTD Tiles Configuration 2.1//EN" "http://tiles.apache.org/dtds/tiles-config_2_1.dtd">
<tiles-definitions>
    <definition extends="default" name="growthphasetranslations/list">
        <put-attribute name="body" value="/WEB-INF/views/growthphasetranslations/list.jspx"/>
    </definition>
<definition extends="default" name="growthphasetranslations/show">
        <put-attribute name="body" value="/WEB-INF/views/growthphasetranslations/show.jspx"/>
    </definition>
<definition extends="default" name="growthphasetranslations/create">
        <put-attribute name="body" value="/WEB-INF/views/growthphasetranslations/create.jspx"/>
    </definition>
<definition extends="default" name="growthphasetranslations/update">
        <put-attribute name="body" value="/WEB-INF/views/growthphasetranslations/update.jspx"/>
    </definition>
</tiles-definitions>
